codario/__init__.py
codario/main.py
codario/controllers/__init__.py
codario/controllers/base.py
codario/controllers/process_task.py
codario/controllers/show_projects.py
codario/controllers/show_tasks.py
codario/controllers/show_workspaces.py
codario/core/__init__.py
codario/core/exc.py
codario/core/version.py
codario/ext/__init__.py
codario/plugins/__init__.py
codario/templates/__init__.py
codario/templates/command1.jinja2
codario-0.1.8.dist-info/LICENSE.md
codario-0.1.8.dist-info/METADATA
codario-0.1.8.dist-info/WHEEL
codario-0.1.8.dist-info/entry_points.txt
codario-0.1.8.dist-info/top_level.txt
codario-0.1.8.dist-info/RECORD
