Metadata-Version: 2.1
Name: codario
Version: 0.1.8
Summary: Codario is a cloud-based service that helps you to stay secure with your open source dependencies.
Home-page: https://codario.io
Author: Alexey Beloglazov
Author-email: alexey.beloglazov@codario.io
License: Apache License 2.0
Platform: UNKNOWN
Requires-Dist: cement
Requires-Dist: colorlog
Requires-Dist: jinja2
Requires-Dist: pyyaml
Requires-Dist: tabulate
Requires-Dist: tinydb
Requires-Dist: urllib3
